interval/__init__.py
interval/utils.py
interval/ddd/__init__.py
interval/ddd/_dto.py
interval/ddd/_entity.py
interval/ddd/_event.py
interval/ddd/_exceptions.py
interval/ddd/_messagebus.py
interval/ddd/_repo.py
interval/ddd/_uow.py
interval/ddd/_valueobject.py
interval_tools-0.17.0.dist-info/licenses/LICENSE
interval_tools-0.17.0.dist-info/METADATA
interval_tools-0.17.0.dist-info/WHEEL
interval_tools-0.17.0.dist-info/top_level.txt
interval_tools-0.17.0.dist-info/RECORD
