Metadata-Version: 2.4
Name: interval-tools
Version: 0.17.0
Summary: Utility functions and classes used in applications of Interval Design.
Author-email: Michael Lyu <lvyao.china@gmail.com>
Project-URL: Homepage, https://github.com/interval-design/python-tools
Classifier: Development Status :: 4 - Beta
Classifier: License :: OSI Approved :: MIT License
Classifier: Operating System :: OS Independent
Classifier: Programming Language :: Python
Classifier: Programming Language :: Python :: 3
Classifier: Programming Language :: Python :: 3 :: Only
Classifier: Programming Language :: Python :: 3.11
Classifier: Programming Language :: Python :: 3.12
Classifier: Programming Language :: Python :: 3.13
Requires-Python: >=3.11
License-File: LICENSE
Requires-Dist: orjson>=3
Provides-Extra: objectid
Requires-Dist: pymongo>=4; extra == "objectid"
Dynamic: license-file
